{"file":"battle_bead.png","frames":{
"baozi_01_png":{"x":211,"y":127,"w":40,"h":40,"offX":0,"offY":0,"sourceW":40,"sourceH":40},
"baozi_02_png":{"x":169,"y":127,"w":40,"h":40,"offX":0,"offY":0,"sourceW":40,"sourceH":40},
"baozi_03_png":{"x":127,"y":127,"w":40,"h":40,"offX":0,"offY":0,"sourceW":40,"sourceH":40},
"baozi_04_png":{"x":85,"y":127,"w":40,"h":40,"offX":0,"offY":0,"sourceW":40,"sourceH":40},
"baozi_05_png":{"x":43,"y":127,"w":40,"h":40,"offX":0,"offY":0,"sourceW":40,"sourceH":40},
"baozi_06_png":{"x":1,"y":127,"w":40,"h":40,"offX":0,"offY":0,"sourceW":40,"sourceH":40},
"baozi_07_png":{"x":164,"y":250,"w":40,"h":37,"offX":0,"offY":2,"sourceW":40,"sourceH":40},
"baozi_08_png":{"x":39,"y":249,"w":40,"h":33,"offX":0,"offY":3,"sourceW":40,"sourceH":40},
"baozi_09_png":{"x":211,"y":85,"w":40,"h":40,"offX":0,"offY":0,"sourceW":40,"sourceH":40},
"baozi_10_png":{"x":169,"y":85,"w":40,"h":40,"offX":0,"offY":0,"sourceW":40,"sourceH":40},
"baozi_11_png":{"x":127,"y":85,"w":40,"h":40,"offX":0,"offY":0,"sourceW":40,"sourceH":40},
"baozi_12_png":{"x":39,"y":211,"w":40,"h":36,"offX":0,"offY":2,"sourceW":40,"sourceH":40},
"baozi_13_png":{"x":85,"y":85,"w":40,"h":40,"offX":0,"offY":0,"sourceW":40,"sourceH":40},
"baozi_14_png":{"x":43,"y":85,"w":40,"h":40,"offX":0,"offY":0,"sourceW":40,"sourceH":40},
"baozi_15_png":{"x":1,"y":85,"w":40,"h":40,"offX":0,"offY":0,"sourceW":40,"sourceH":40},
"baozi_16_png":{"x":164,"y":210,"w":40,"h":38,"offX":0,"offY":0,"sourceW":40,"sourceH":40},
"baozi_17_png":{"x":211,"y":43,"w":40,"h":40,"offX":0,"offY":0,"sourceW":40,"sourceH":40},
"baozi_18_png":{"x":169,"y":43,"w":40,"h":40,"offX":0,"offY":0,"sourceW":40,"sourceH":40},
"baozi_19_png":{"x":127,"y":43,"w":40,"h":40,"offX":0,"offY":0,"sourceW":40,"sourceH":40},
"baozi_20_png":{"x":85,"y":43,"w":40,"h":40,"offX":0,"offY":0,"sourceW":40,"sourceH":40},
"baozi_21_png":{"x":43,"y":43,"w":40,"h":40,"offX":0,"offY":0,"sourceW":40,"sourceH":40},
"baozi_22_png":{"x":1,"y":43,"w":40,"h":40,"offX":0,"offY":0,"sourceW":40,"sourceH":40},
"baozi_23_png":{"x":42,"y":169,"w":39,"h":40,"offX":1,"offY":0,"sourceW":40,"sourceH":40},
"baozi_24_png":{"x":124,"y":210,"w":38,"h":40,"offX":1,"offY":0,"sourceW":40,"sourceH":40},
"baozi_25_png":{"x":1,"y":211,"w":36,"h":40,"offX":2,"offY":0,"sourceW":40,"sourceH":40},
"baozi_26_png":{"x":1,"y":169,"w":39,"h":40,"offX":0,"offY":0,"sourceW":40,"sourceH":40},
"baozi_27_png":{"x":206,"y":249,"w":40,"h":37,"offX":0,"offY":0,"sourceW":40,"sourceH":40},
"baozi_28_png":{"x":211,"y":1,"w":40,"h":40,"offX":0,"offY":0,"sourceW":40,"sourceH":40},
"baozi_29_png":{"x":169,"y":1,"w":40,"h":40,"offX":0,"offY":0,"sourceW":40,"sourceH":40},
"baozi_30_png":{"x":83,"y":169,"w":39,"h":40,"offX":1,"offY":0,"sourceW":40,"sourceH":40},
"baozi_31_png":{"x":166,"y":169,"w":40,"h":39,"offX":0,"offY":0,"sourceW":40,"sourceH":40},
"baozi_32_png":{"x":127,"y":1,"w":40,"h":40,"offX":0,"offY":0,"sourceW":40,"sourceH":40},
"baozi_33_png":{"x":85,"y":1,"w":40,"h":40,"offX":0,"offY":0,"sourceW":40,"sourceH":40},
"baozi_34_png":{"x":124,"y":169,"w":40,"h":39,"offX":0,"offY":0,"sourceW":40,"sourceH":40},
"baozi_35_png":{"x":206,"y":210,"w":40,"h":37,"offX":0,"offY":2,"sourceW":40,"sourceH":40},
"baozi_36_png":{"x":43,"y":1,"w":40,"h":40,"offX":0,"offY":0,"sourceW":40,"sourceH":40},
"baozi_37_png":{"x":81,"y":249,"w":39,"h":30,"offX":0,"offY":6,"sourceW":40,"sourceH":40},
"baozi_38_png":{"x":206,"y":288,"w":37,"h":39,"offX":1,"offY":0,"sourceW":40,"sourceH":40},
"baozi_39_png":{"x":1,"y":1,"w":40,"h":40,"offX":0,"offY":0,"sourceW":40,"sourceH":40},
"baozi_40_png":{"x":81,"y":211,"w":40,"h":36,"offX":0,"offY":1,"sourceW":40,"sourceH":40},
"baozi_41_png":{"x":208,"y":169,"w":39,"h":39,"offX":1,"offY":0,"sourceW":40,"sourceH":40}}}